melon/__init__.py
melon/calendar.py
melon/config.py
melon/melon.py
melon/scheduler/__init__.py
melon/scheduler/base.py
melon/scheduler/cpp.py
melon/scheduler/libcppscheduler.cpp
melon/scheduler/libcppscheduler.pyi
melon/scheduler/libcppscheduler.so
melon/scheduler/libscheduler.pyi
melon/scheduler/libscheduler.rs
melon/scheduler/libscheduler.so
melon/scheduler/numba.py
melon/scheduler/purepython.py
melon/scheduler/rust.py
melon/todo.py
melon/visualise.py
melongui/__init__.py
melongui/assets/complete.png
melongui/assets/complete.svg
melongui/calendarlist.py
melongui/main.py
melongui/mainwindow.py
melongui/taskitemdelegate.py
melongui/tasklist.py
melongui/taskwidgets.py
melon_scheduler-0.2.0.dist-info/METADATA
melon_scheduler-0.2.0.dist-info/WHEEL
melon_scheduler-0.2.0.dist-info/RECORD
