Metadata-Version: 2.1
Name: melon-scheduler
Version: 0.2.0
Summary: Schedules Todos into your Calendar
Author: redacted
Requires-Python: >=3.10,<3.12
Classifier: Programming Language :: Python :: 3
Classifier: Programming Language :: Python :: 3.10
Classifier: Programming Language :: Python :: 3.11
Provides-Extra: gui
Provides-Extra: numba
Provides-Extra: plots
Requires-Dist: caldav (>=1.2.1,<2.0.0)
Requires-Dist: dateparser (>=1.1.8,<2.0.0)
Requires-Dist: matplotlib (>=3.7.1,<4.0.0) ; extra == "plots"
Requires-Dist: numba (>=0.57.1,<0.58.0) ; extra == "numba"
Requires-Dist: pyside6 (<6.5) ; extra == "gui"
Requires-Dist: tomli (>=2.0.1,<3.0.0) ; python_version < "3.11"
Requires-Dist: tqdm (>=4.65.0,<5.0.0)
